odoo/addons/partner_bank_active/README.rst
odoo/addons/partner_bank_active/__init__.py
odoo/addons/partner_bank_active/__manifest__.py
odoo/addons/partner_bank_active/i18n/ar.po
odoo/addons/partner_bank_active/i18n/bg.po
odoo/addons/partner_bank_active/i18n/bs.po
odoo/addons/partner_bank_active/i18n/ca.po
odoo/addons/partner_bank_active/i18n/cs.po
odoo/addons/partner_bank_active/i18n/da.po
odoo/addons/partner_bank_active/i18n/de.po
odoo/addons/partner_bank_active/i18n/en_GB.po
odoo/addons/partner_bank_active/i18n/es.po
odoo/addons/partner_bank_active/i18n/es_CR.po
odoo/addons/partner_bank_active/i18n/es_EC.po
odoo/addons/partner_bank_active/i18n/es_ES.po
odoo/addons/partner_bank_active/i18n/es_MX.po
odoo/addons/partner_bank_active/i18n/es_VE.po
odoo/addons/partner_bank_active/i18n/et.po
odoo/addons/partner_bank_active/i18n/fi.po
odoo/addons/partner_bank_active/i18n/fr.po
odoo/addons/partner_bank_active/i18n/fr_CH.po
odoo/addons/partner_bank_active/i18n/gl.po
odoo/addons/partner_bank_active/i18n/hr.po
odoo/addons/partner_bank_active/i18n/hr_HR.po
odoo/addons/partner_bank_active/i18n/hu.po
odoo/addons/partner_bank_active/i18n/id.po
odoo/addons/partner_bank_active/i18n/it.po
odoo/addons/partner_bank_active/i18n/ja.po
odoo/addons/partner_bank_active/i18n/lt.po
odoo/addons/partner_bank_active/i18n/lv.po
odoo/addons/partner_bank_active/i18n/mk.po
odoo/addons/partner_bank_active/i18n/mn.po
odoo/addons/partner_bank_active/i18n/nb.po
odoo/addons/partner_bank_active/i18n/nb_NO.po
odoo/addons/partner_bank_active/i18n/nl.po
odoo/addons/partner_bank_active/i18n/nl_BE.po
odoo/addons/partner_bank_active/i18n/nl_NL.po
odoo/addons/partner_bank_active/i18n/partner_bank_active.pot
odoo/addons/partner_bank_active/i18n/pl.po
odoo/addons/partner_bank_active/i18n/pt.po
odoo/addons/partner_bank_active/i18n/pt_BR.po
odoo/addons/partner_bank_active/i18n/pt_PT.po
odoo/addons/partner_bank_active/i18n/ro.po
odoo/addons/partner_bank_active/i18n/ru.po
odoo/addons/partner_bank_active/i18n/sk.po
odoo12_addon_partner_bank_active-12.0.1.0.0.99.dev7.dist-info/METADATA
odoo12_addon_partner_bank_active-12.0.1.0.0.99.dev7.dist-info/WHEEL
odoo12_addon_partner_bank_active-12.0.1.0.0.99.dev7.dist-info/top_level.txt
odoo12_addon_partner_bank_active-12.0.1.0.0.99.dev7.dist-info/RECORD
