Metadata-Version: 2.1
Name: odoo12-addon-partner-bank-active
Version: 12.0.1.0.0.99.dev7
Summary: This module allows to deactivate a partner bank account.
Home-page: https://github.com/OCA/partner-contact
Author: ACSONE SA/NV, Odoo Community Association (OCA)
Author-email: support@odoo-community.org
License: AGPL-3
Platform: UNKNOWN
Classifier: Programming Language :: Python
Classifier: Framework :: Odoo
Classifier: Framework :: Odoo :: 12.0
Classifier: License :: OSI Approved :: GNU Affero General Public License v3
Classifier: Development Status :: 5 - Production/Stable
Requires-Python: >=3.5
Requires-Dist: odoo <12.1dev,>=12.0a
